wetter/__init__.py
wetter/app.py
wetter/backend/__init__.py
wetter/backend/extern.py
wetter/backend/local.py
wetter/backend/queries.py
wetter/config/__init__.py
wetter/config/config.py
wetter/config/defaults.py
wetter/config/parser.py
wetter/tools.py
wetter-0.4.1.dist-info/METADATA
wetter-0.4.1.dist-info/WHEEL
wetter-0.4.1.dist-info/entry_points.txt
wetter-0.4.1.dist-info/RECORD
