Metadata-Version: 2.1
Name: wetter
Version: 0.4.1
Summary: CLI tool to parse weather data
Home-page: https://github.com/ucyo/wetter-py
License: MIT
Author: Uğur Çayoğlu
Author-email: cayoglu@me.com
Requires-Python: >=3.8.1,<4.0.0
Classifier: Development Status :: 3 - Alpha
Classifier: Intended Audience :: Science/Research
Classifier: License :: OSI Approved :: MIT License
Classifier: Operating System :: OS Independent
Classifier: Programming Language :: Python
Classifier: Programming Language :: Python :: 3
Classifier: Programming Language :: Python :: 3.9
Classifier: Programming Language :: Python :: 3.10
Classifier: Programming Language :: Python :: 3.11
Classifier: Programming Language :: Python :: 3
Classifier: Programming Language :: Python :: 3.10
Classifier: Programming Language :: Python :: 3.11
Classifier: Programming Language :: Python :: 3.8
Classifier: Programming Language :: Python :: 3.9
Classifier: Topic :: Scientific/Engineering
Requires-Dist: Bottleneck (>=1.3.7,<2.0.0)
Requires-Dist: numexpr (>=2.8.4,<3.0.0)
Requires-Dist: pandas (>=1.5.3,<2.0.0)
Requires-Dist: platformdirs (>=3.2.0,<4.0.0)
Requires-Dist: requests (>=2.28.2,<3.0.0)
Requires-Dist: toml (>=0.10.2,<0.11.0)
Project-URL: Documentation, https://github.com/ucyo/wetter-py
Project-URL: Repository, https://github.com/ucyo/wetter-py
